objdbg/__init__.py
objdbg/objdbg.py
objdbg-0.1.2.1.dist-info/LICENSE
objdbg-0.1.2.1.dist-info/METADATA
objdbg-0.1.2.1.dist-info/WHEEL
objdbg-0.1.2.1.dist-info/top_level.txt
objdbg-0.1.2.1.dist-info/RECORD
