Metadata-Version: 2.1
Name: objdbg
Version: 0.1.2.1
Summary: Object debugger in python
Home-page: https://github.com/LamentXU123/objdbg
Author: LamentXU
Author-email: 1372449351@qq.com
License: UNKNOWN
Platform: UNKNOWN
Classifier: Programming Language :: Python :: 3
Classifier: Operating System :: OS Independent
Requires-Dist: objprint==0.3.0
Requires-Dist: rich==13.7.1
